xronos/__init__.py
xronos/_core.py
xronos/_cpp_sdk.cpython-313t-aarch64-linux-gnu.so
xronos/_cpp_sdk.pyi
xronos/py.typed
xronos/lib/__init__.py
xronos/lib/_abstract_source.py
xronos/lib/_external_input.py
xronos/lib/_simple_source.py
xronos/lib/_socket_input.py
xronos/lib/test/test_external_input.py
xronos/lib/test/test_simple_source.py
xronos/lib/test/test_socket_input.py
xronos/lib/test/util.py
xronos/test/test_reaction.py
xronos/test/test_reactor.py
xronos.libs/libxronos-sdk-b9c926db.so.0.8.0
xronos-0.8.0.dist-info/METADATA
xronos-0.8.0.dist-info/WHEEL
xronos-0.8.0.dist-info/RECORD
xronos-0.8.0.dist-info/licenses/LICENSE
xronos-0.8.0.dist-info/licenses/THIRD_PARTY_NOTICE
xronos-0.8.0.dist-info/licenses/third-party-licenses/abseil_LICENSE
xronos-0.8.0.dist-info/licenses/third-party-licenses/address_sorting_LICENSE
xronos-0.8.0.dist-info/licenses/third-party-licenses/boringssl_LICENSE
xronos-0.8.0.dist-info/licenses/third-party-licenses/expected-lite_LICENSE
xronos-0.8.0.dist-info/licenses/third-party-licenses/fmt_LICENSE
xronos-0.8.0.dist-info/licenses/third-party-licenses/grpc_LICENSE
xronos-0.8.0.dist-info/licenses/third-party-licenses/grpc_NOTICE
xronos-0.8.0.dist-info/licenses/third-party-licenses/myst_parser_LICENSE
xronos-0.8.0.dist-info/licenses/third-party-licenses/opentelemetry_cpp_LICENSE
xronos-0.8.0.dist-info/licenses/third-party-licenses/opentelemetry_proto_LICENSE
xronos-0.8.0.dist-info/licenses/third-party-licenses/protobuf_LICENSE
xronos-0.8.0.dist-info/licenses/third-party-licenses/pybind11_LICENSE
xronos-0.8.0.dist-info/licenses/third-party-licenses/re2_LICENSE
xronos-0.8.0.dist-info/licenses/third-party-licenses/reactor_cpp_LICENSE
xronos-0.8.0.dist-info/licenses/third-party-licenses/sphinx_copybutton_LICENSE
xronos-0.8.0.dist-info/licenses/third-party-licenses/sphinx_rtd_theme_LICENSE
xronos-0.8.0.dist-info/licenses/third-party-licenses/sphinx_tabs_LICENSE
xronos-0.8.0.dist-info/licenses/third-party-licenses/utf8_range_LICENSE
