Metadata-Version: 2.2
Name: xronos
Version: 0.8.0
Summary: Reactors for Python
Author-Email: Christian Menard <christian@xronos.com>, Peter Donovan <peter@xronos.com>, "Jeff C. Jensen" <elgeeko@xronos.com>, Erling Jellum <erling@xronos.com>
Maintainer-Email: Christian Menard <christian@xronos.com>
License: BSD 3-Clause License
Classifier: Development Status :: 3 - Alpha
Classifier: Intended Audience :: Developers
Classifier: License :: OSI Approved :: BSD License
Classifier: Programming Language :: Python :: 3
Classifier: Programming Language :: Python :: 3.10
Classifier: Programming Language :: Python :: 3.11
Classifier: Programming Language :: Python :: 3.12
Classifier: Programming Language :: Python :: 3.13
Classifier: Programming Language :: Python :: 3.14
Classifier: Programming Language :: Python :: Free Threading
Classifier: Programming Language :: Python :: Free Threading :: 3 - Stable
Classifier: Operating System :: POSIX :: Linux
Classifier: Topic :: Scientific/Engineering
Classifier: Topic :: Software Development :: Embedded Systems
Classifier: Topic :: Software Development :: Libraries :: Application Frameworks
Classifier: Topic :: Software Development :: Libraries :: Python Modules
Classifier: Typing :: Typed
Project-URL: Homepage, https://xronos.com
Project-URL: Repository, https://github.com/xronos-inc/xronos
Project-URL: Documentation, https://xronos-inc.github.io/xronos/index.html
Requires-Python: >=3.10
Requires-Dist: typing-extensions>=4.5.0
Provides-Extra: dashboard
Requires-Dist: xronos-dashboard==0.8.0; extra == "dashboard"
